README.md
setup.py
okp/__init__.py
okp/analysis.py
okp/config.py
okp/id_recognizer.py
okp/lines.py
okp/main.py
okp/main_impl.py
okp/pipeline.py
okp/project.py
okp/single_header.py
okp/test_runner.py
okp/util.py
okp/version.py
okp.egg-info/PKG-INFO
okp.egg-info/SOURCES.txt
okp.egg-info/dependency_links.txt
okp.egg-info/requires.txt
okp.egg-info/top_level.txt
okp/linters/__init__.py
okp/linters/clanger.py
okp/linters/class_vars_without_this.py
okp/transforms/__init__.py
okp/transforms/comments.py
okp/transforms/io.py
okp/transforms/keywords.py
okp/transforms/structure.py
okp/transforms/variables.py
scripts/okp