Metadata-Version: 2.1
Name: okp
Version: 0.0.44
Summary: an compiler for .cpy files
Home-page: http://github.com/okayzed/okp
Author: okay
Author-email: okayzed+okp@gmail.com
License: MIT
Platform: UNKNOWN
